SQLly/SQLly.py
SQLly-0.3.dist-info/METADATA
SQLly-0.3.dist-info/WHEEL
SQLly-0.3.dist-info/top_level.txt
SQLly-0.3.dist-info/RECORD
