Metadata-Version: 2.1
Name: SQLly
Version: 0.3
Summary: A Python library for working with SQL/noSQL databases
Home-page: UNKNOWN
Author: Bektaş Kara
Author-email: bektaskara4@gmail.com
License: UNKNOWN
Platform: UNKNOWN
Requires-Dist: mysql.connector
Requires-Dist: psycopg2-binary
Requires-Dist: colorama
